dmcast
